pytest_bisect_tests/__init__.py
pytest_bisect_tests/bisect.py
pytest_bisect_tests/cli.py
pytest_bisect_tests/pytest_plugin.py
pytest_bisect_tests/pytest_runner.py
pytest_bisect_tests-0.3.0.dist-info/LICENSE
pytest_bisect_tests-0.3.0.dist-info/METADATA
pytest_bisect_tests-0.3.0.dist-info/WHEEL
pytest_bisect_tests-0.3.0.dist-info/entry_points.txt
pytest_bisect_tests-0.3.0.dist-info/top_level.txt
pytest_bisect_tests-0.3.0.dist-info/RECORD
