Metadata-Version: 2.1
Name: pytest-bisect-tests
Version: 0.3.0
Summary: Find tests leaking state and affecting other
Author-email: Maciej Gol <suchar.kroolik1@gmail.com>
Project-URL: Homepage, https://github.com/maciej-gol/pytest-bisect-tests
Project-URL: Issues, https://github.com/maciej-gol/pytest-bisect-tests/issues
Classifier: Framework :: Pytest
Classifier: Programming Language :: Python :: 3
Classifier: License :: OSI Approved :: MIT License
Classifier: Operating System :: OS Independent
Requires-Python: >=3.8
License-File: LICENSE
